{
   "Grignone" : {
      "Acquafredda" : { 
         "it" : "http://grignone-pasturo.blogspot.it/2015/07/{self}.html",
         "en" : "http://en-grignone-pasturo.blogspot.it/2015/07/{self}.html"
      },
      "Agriturismo Brunino" : { 
         "it" : "http://grignone-pasturo.blogspot.it/2015/06/{self}.html",
         "en" : "http://en-grignone-pasturo.blogspot.it/2015/06/{self}.html"
      },
      "Alpe Cova" : { 
         "it" : "http://grignone-pasturo.blogspot.it/2015/07/{self}.html",
         "en" : "http://en-grignone-pasturo.blogspot.it/2015/07/{self}.html"
      }
   }
}
